<?xml version="1.0" encoding="utf-8"?>
<GameInfo>
	<IconTextureAtlases>
		<Row Name="ICON_ATLAS_GREATWORKS" IconSize="45" IconsPerRow="8" IconsPerColumn="8" Filename="GreatWorks45"/>
		<Row Name="ICON_ATLAS_GREATWORKS_2" IconSize="45" IconsPerRow="8" IconsPerColumn="8" Filename="GreatWorks45_2"/>
		<Row Name="ICON_ATLAS_GREATWORKS" IconSize="64" IconsPerRow="8" IconsPerColumn="8" Filename="GreatWorks64"/>
		<Row Name="ICON_ATLAS_GREATWORKS_2" IconSize="64" IconsPerRow="8" IconsPerColumn="8" Filename="GreatWorks64_2"/>
		<Row Name="ICON_ATLAS_GREATWORKS" IconSize="256" IconsPerRow="8" IconsPerColumn="8" Filename="GreatWorks256"/>
		<Row Name="ICON_ATLAS_GREATWORKS_2" IconSize="256" IconsPerRow="8" IconsPerColumn="8" Filename="GreatWorks256_2"/>
	</IconTextureAtlases>
	<IconDefinitions>
		<Row Name="ICON_GREATWORK_BHASA_2"				Atlas="ICON_ATLAS_GREATWORKS"			Index="0"/>
		<Row Name="ICON_GREATWORK_BHASA_1"				Atlas="ICON_ATLAS_GREATWORKS"			Index="0"/>
		<Row Name="ICON_GREATWORK_HOMER_1"				Atlas="ICON_ATLAS_GREATWORKS"			Index="0"/>
		<Row Name="ICON_GREATWORK_HOMER_2"				Atlas="ICON_ATLAS_GREATWORKS"			Index="0"/>
		<Row Name="ICON_GREATWORK_OVID_1"					Atlas="ICON_ATLAS_GREATWORKS"			Index="0"/>
		<Row Name="ICON_GREATWORK_OVID_2"					Atlas="ICON_ATLAS_GREATWORKS"			Index="0"/>
		<Row Name="ICON_GREATWORK_QU_YUAN_1"			Atlas="ICON_ATLAS_GREATWORKS"			Index="0"/>
		<Row Name="ICON_GREATWORK_QU_YUAN_2"			Atlas="ICON_ATLAS_GREATWORKS"			Index="0"/>
		<Row Name="ICON_GREATWORK_CHAUCER_1"			Atlas="ICON_ATLAS_GREATWORKS"			Index="0"/>
		<Row Name="ICON_GREATWORK_CHAUCER_2"			Atlas="ICON_ATLAS_GREATWORKS"			Index="0"/>
		<Row Name="ICON_GREATWORK_LI_BAI_1"				Atlas="ICON_ATLAS_GREATWORKS"			Index="0"/>
		<Row Name="ICON_GREATWORK_LI_BAI_2"				Atlas="ICON_ATLAS_GREATWORKS"			Index="0"/>
		<Row Name="ICON_GREATWORK_D_AULNOY_1"				Atlas="ICON_ATLAS_GREATWORKS"			Index="0"/>
		<Row Name="ICON_GREATWORK_D_AULNOY_2"				Atlas="ICON_ATLAS_GREATWORKS"			Index="0"/>
		<Row Name="ICON_GREATWORK_MURASAKI_1"			Atlas="ICON_ATLAS_GREATWORKS"			Index="0"/>
		<Row Name="ICON_GREATWORK_MURASAKI_2"			Atlas="ICON_ATLAS_GREATWORKS"			Index="0"/>
		<Row Name="ICON_GREATWORK_CAVENDISH_1"		Atlas="ICON_ATLAS_GREATWORKS"			Index="0"/>
		<Row Name="ICON_GREATWORK_CAVENDISH_2"		Atlas="ICON_ATLAS_GREATWORKS"			Index="0"/>
		<Row Name="ICON_GREATWORK_CERVANTES_1"		Atlas="ICON_ATLAS_GREATWORKS"			Index="0"/>
		<Row Name="ICON_GREATWORK_CERVANTES_2"		Atlas="ICON_ATLAS_GREATWORKS"			Index="0"/>
		<Row Name="ICON_GREATWORK_MACHIAVELLI_1"	Atlas="ICON_ATLAS_GREATWORKS"			Index="0"/>
		<Row Name="ICON_GREATWORK_MACHIAVELLI_2"	Atlas="ICON_ATLAS_GREATWORKS"			Index="0"/>
		<Row Name="ICON_GREATWORK_SHAKESPEARE_1"	Atlas="ICON_ATLAS_GREATWORKS"			Index="0"/>
		<Row Name="ICON_GREATWORK_SHAKESPEARE_2"	Atlas="ICON_ATLAS_GREATWORKS"			Index="0"/>
		<Row Name="ICON_GREATWORK_PUSHKIN_1"			Atlas="ICON_ATLAS_GREATWORKS"			Index="0"/>
		<Row Name="ICON_GREATWORK_PUSHKIN_2"			Atlas="ICON_ATLAS_GREATWORKS"			Index="0"/>
		<Row Name="ICON_GREATWORK_POE_1"					Atlas="ICON_ATLAS_GREATWORKS"			Index="0"/>
		<Row Name="ICON_GREATWORK_POE_2"					Atlas="ICON_ATLAS_GREATWORKS"			Index="0"/>
		<Row Name="ICON_GREATWORK_AUSTEN_1"				Atlas="ICON_ATLAS_GREATWORKS"			Index="0"/>
		<Row Name="ICON_GREATWORK_AUSTEN_2"				Atlas="ICON_ATLAS_GREATWORKS"			Index="0"/>
		<Row Name="ICON_GREATWORK_SHELLEY_1"				Atlas="ICON_ATLAS_GREATWORKS"			Index="0"/>
		<Row Name="ICON_GREATWORK_SHELLEY_2"				Atlas="ICON_ATLAS_GREATWORKS"			Index="0"/>
		<Row Name="ICON_GREATWORK_GOETHE_1"				Atlas="ICON_ATLAS_GREATWORKS"			Index="0"/>
		<Row Name="ICON_GREATWORK_GOETHE_2"				Atlas="ICON_ATLAS_GREATWORKS"			Index="0"/>
		<Row Name="ICON_GREATWORK_MUIS_1"					Atlas="ICON_ATLAS_GREATWORKS"			Index="0"/>
		<Row Name="ICON_GREATWORK_MUIS_2"					Atlas="ICON_ATLAS_GREATWORKS"			Index="0"/>
		<Row Name="ICON_GREATWORK_DICKINSON_1"		Atlas="ICON_ATLAS_GREATWORKS"			Index="0"/>
		<Row Name="ICON_GREATWORK_DICKINSON_2"		Atlas="ICON_ATLAS_GREATWORKS"			Index="0"/>
		<Row Name="ICON_GREATWORK_TOLSTOY_1"			Atlas="ICON_ATLAS_GREATWORKS"			Index="0"/>
		<Row Name="ICON_GREATWORK_TOLSTOY_2"			Atlas="ICON_ATLAS_GREATWORKS"			Index="0"/>
		<Row Name="ICON_GREATWORK_TWAIN_1"				Atlas="ICON_ATLAS_GREATWORKS"			Index="0"/>
		<Row Name="ICON_GREATWORK_TWAIN_2"				Atlas="ICON_ATLAS_GREATWORKS"			Index="0"/>
		<Row Name="ICON_GREATWORK_WELLS_1"				Atlas="ICON_ATLAS_GREATWORKS"			Index="0"/>
		<Row Name="ICON_GREATWORK_WELLS_2"				Atlas="ICON_ATLAS_GREATWORKS"			Index="0"/>
		<Row Name="ICON_GREATWORK_JOYCE_1"				Atlas="ICON_ATLAS_GREATWORKS"			Index="0"/>
		<Row Name="ICON_GREATWORK_JOYCE_2"				Atlas="ICON_ATLAS_GREATWORKS"			Index="0"/>
		<Row Name="ICON_GREATWORK_TAGORE_1"				Atlas="ICON_ATLAS_GREATWORKS"			Index="0"/>
		<Row Name="ICON_GREATWORK_TAGORE_2"				Atlas="ICON_ATLAS_GREATWORKS"			Index="0"/>
		<Row Name="ICON_GREATWORK_UNDSET_1"				Atlas="ICON_ATLAS_GREATWORKS"			Index="0"/>
		<Row Name="ICON_GREATWORK_UNDSET_2"				Atlas="ICON_ATLAS_GREATWORKS"			Index="0"/>
		<Row Name="ICON_GREATWORK_CHRISTIE_1"			Atlas="ICON_ATLAS_GREATWORKS"			Index="0"/>
		<Row Name="ICON_GREATWORK_CHRISTIE_2"			Atlas="ICON_ATLAS_GREATWORKS"			Index="0"/>
		<Row Name="ICON_GREATWORK_MISTRAL_1"			Atlas="ICON_ATLAS_GREATWORKS"			Index="0"/>
		<Row Name="ICON_GREATWORK_MISTRAL_2"			Atlas="ICON_ATLAS_GREATWORKS"			Index="0"/>
		<Row Name="ICON_GREATWORK_CAPEK_1"				Atlas="ICON_ATLAS_GREATWORKS"			Index="0"/>
		<Row Name="ICON_GREATWORK_CAPEK_2"				Atlas="ICON_ATLAS_GREATWORKS"			Index="0"/>
		<Row Name="ICON_GREATWORK_BLIXEN_1"				Atlas="ICON_ATLAS_GREATWORKS"			Index="0"/>
		<Row Name="ICON_GREATWORK_BLIXEN_2"				Atlas="ICON_ATLAS_GREATWORKS"			Index="0"/>
		<Row Name="ICON_GREATWORK_SUN_TZU"				Atlas="ICON_ATLAS_GREATWORKS"			Index="0"/>
		<Row Name="ICON_GREATWORK_FITZGERALD_1"				Atlas="ICON_ATLAS_GREATWORKS"			Index="0"/>
		<Row Name="ICON_GREATWORK_FITZGERALD_2"				Atlas="ICON_ATLAS_GREATWORKS"			Index="0"/>
		<Row Name="ICON_GREATWORK_RUBLEV_1"				Atlas="ICON_ATLAS_GREATWORKS"			Index="14"/>
		<Row Name="ICON_GREATWORK_RUBLEV_2"				Atlas="ICON_ATLAS_GREATWORKS"			Index="15"/>
		<Row Name="ICON_GREATWORK_RUBLEV_3"				Atlas="ICON_ATLAS_GREATWORKS"			Index="16"/>
		<Row Name="ICON_GREATWORK_BOSCH_1"				Atlas="ICON_ATLAS_GREATWORKS"			Index="17"/>
		<Row Name="ICON_GREATWORK_BOSCH_2"				Atlas="ICON_ATLAS_GREATWORKS"			Index="18"/>
		<Row Name="ICON_GREATWORK_BOSCH_3"				Atlas="ICON_ATLAS_GREATWORKS"			Index="19"/>
		<Row Name="ICON_GREATWORK_DONATELLO_1"		Atlas="ICON_ATLAS_GREATWORKS"			Index="20"/>
		<Row Name="ICON_GREATWORK_DONATELLO_2"		Atlas="ICON_ATLAS_GREATWORKS"			Index="21"/>
		<Row Name="ICON_GREATWORK_DONATELLO_3"		Atlas="ICON_ATLAS_GREATWORKS"			Index="22"/>
		<Row Name="ICON_GREATWORK_MICHELANGELO_1"	Atlas="ICON_ATLAS_GREATWORKS"			Index="23"/>
		<Row Name="ICON_GREATWORK_MICHELANGELO_2"	Atlas="ICON_ATLAS_GREATWORKS"			Index="24"/>
		<Row Name="ICON_GREATWORK_MICHELANGELO_3"	Atlas="ICON_ATLAS_GREATWORKS"			Index="25"/>
		<Row Name="ICON_GREATWORK_YING_1"					Atlas="ICON_ATLAS_GREATWORKS"			Index="26"/>
		<Row Name="ICON_GREATWORK_YING_2"					Atlas="ICON_ATLAS_GREATWORKS"			Index="27"/>
		<Row Name="ICON_GREATWORK_YING_3"					Atlas="ICON_ATLAS_GREATWORKS"			Index="28"/>
		<Row Name="ICON_GREATWORK_TITIAN_1"				Atlas="ICON_ATLAS_GREATWORKS"			Index="29"/>
		<Row Name="ICON_GREATWORK_TITIAN_2"				Atlas="ICON_ATLAS_GREATWORKS"			Index="30"/>
		<Row Name="ICON_GREATWORK_TITIAN_3"				Atlas="ICON_ATLAS_GREATWORKS"			Index="31"/>
		<Row Name="ICON_GREATWORK_GRECO_1"				Atlas="ICON_ATLAS_GREATWORKS"			Index="32"/>
		<Row Name="ICON_GREATWORK_GRECO_2"				Atlas="ICON_ATLAS_GREATWORKS"			Index="33"/>
		<Row Name="ICON_GREATWORK_GRECO_3"				Atlas="ICON_ATLAS_GREATWORKS"			Index="34"/>
		<Row Name="ICON_GREATWORK_REMBRANDT_1"		Atlas="ICON_ATLAS_GREATWORKS"			Index="35"/>
		<Row Name="ICON_GREATWORK_REMBRANDT_2"		Atlas="ICON_ATLAS_GREATWORKS"			Index="36"/>
		<Row Name="ICON_GREATWORK_REMBRANDT_3"		Atlas="ICON_ATLAS_GREATWORKS"			Index="37"/>
		<Row Name="ICON_GREATWORK_ANGUISSOLA_1"		Atlas="ICON_ATLAS_GREATWORKS"			Index="38"/>
		<Row Name="ICON_GREATWORK_ANGUISSOLA_2"		Atlas="ICON_ATLAS_GREATWORKS"			Index="39"/>
		<Row Name="ICON_GREATWORK_ANGUISSOLA_3"		Atlas="ICON_ATLAS_GREATWORKS"			Index="40"/>
		<Row Name="ICON_GREATWORK_KAUFFMAN_1"			Atlas="ICON_ATLAS_GREATWORKS"			Index="41"/>
		<Row Name="ICON_GREATWORK_KAUFFMAN_2"			Atlas="ICON_ATLAS_GREATWORKS"			Index="42"/>
		<Row Name="ICON_GREATWORK_KAUFFMAN_3"			Atlas="ICON_ATLAS_GREATWORKS"			Index="43"/>
		<Row Name="ICON_GREATWORK_HOKUSAI_1"			Atlas="ICON_ATLAS_GREATWORKS"			Index="44"/>
		<Row Name="ICON_GREATWORK_HOKUSAI_2"			Atlas="ICON_ATLAS_GREATWORKS"			Index="45"/>
		<Row Name="ICON_GREATWORK_HOKUSAI_3"			Atlas="ICON_ATLAS_GREATWORKS"			Index="46"/>
		<Row Name="ICON_GREATWORK_EOP_1"					Atlas="ICON_ATLAS_GREATWORKS"			Index="47"/>
		<Row Name="ICON_GREATWORK_EOP_2"					Atlas="ICON_ATLAS_GREATWORKS"			Index="48"/>
		<Row Name="ICON_GREATWORK_EOP_3"					Atlas="ICON_ATLAS_GREATWORKS"			Index="49"/>
		<Row Name="ICON_GREATWORK_GOGH_1"					Atlas="ICON_ATLAS_GREATWORKS"			Index="50"/>
		<Row Name="ICON_GREATWORK_GOGH_2"					Atlas="ICON_ATLAS_GREATWORKS"			Index="51"/>
		<Row Name="ICON_GREATWORK_GOGH_3"					Atlas="ICON_ATLAS_GREATWORKS"			Index="52"/>
		<Row Name="ICON_GREATWORK_LEWIS_1"				Atlas="ICON_ATLAS_GREATWORKS"			Index="53"/>
		<Row Name="ICON_GREATWORK_LEWIS_2"				Atlas="ICON_ATLAS_GREATWORKS"			Index="54"/>
		<Row Name="ICON_GREATWORK_LEWIS_3"				Atlas="ICON_ATLAS_GREATWORKS"			Index="55"/>
		<Row Name="ICON_GREATWORK_COLLOT_1"				Atlas="ICON_ATLAS_GREATWORKS"			Index="56"/>
		<Row Name="ICON_GREATWORK_COLLOT_2"				Atlas="ICON_ATLAS_GREATWORKS"			Index="57"/>
		<Row Name="ICON_GREATWORK_COLLOT_3"				Atlas="ICON_ATLAS_GREATWORKS"			Index="58"/>
		<Row Name="ICON_GREATWORK_MONET_1"			Atlas="ICON_ATLAS_GREATWORKS"			Index="59"/>
		<Row Name="ICON_GREATWORK_MONET_2"			Atlas="ICON_ATLAS_GREATWORKS"			Index="60"/>
		<Row Name="ICON_GREATWORK_MONET_3"			Atlas="ICON_ATLAS_GREATWORKS"			Index="61"/>
		<Row Name="ICON_GREATWORK_ORLOVSKY_1"				Atlas="ICON_ATLAS_GREATWORKS"			Index="62"/>
		<Row Name="ICON_GREATWORK_ORLOVSKY_2"				Atlas="ICON_ATLAS_GREATWORKS"			Index="63"/>
		<Row Name="ICON_GREATWORK_ORLOVSKY_3"				Atlas="ICON_ATLAS_GREATWORKS_2"			Index="0"/>
		<Row Name="ICON_GREATWORK_KLIMT_1"				Atlas="ICON_ATLAS_GREATWORKS_2"			Index="1"/>
		<Row Name="ICON_GREATWORK_KLIMT_2"				Atlas="ICON_ATLAS_GREATWORKS_2"			Index="2"/>
		<Row Name="ICON_GREATWORK_KLIMT_3"				Atlas="ICON_ATLAS_GREATWORKS_2"			Index="3"/>
		<Row Name="ICON_GREATWORK_GIL_1"					Atlas="ICON_ATLAS_GREATWORKS_2"			Index="4"/>
		<Row Name="ICON_GREATWORK_GIL_2"					Atlas="ICON_ATLAS_GREATWORKS_2"			Index="5"/>
		<Row Name="ICON_GREATWORK_GIL_3"					Atlas="ICON_ATLAS_GREATWORKS_2"			Index="6"/>
		<Row Name="ICON_GREATWORK_CASSATT_1"			Atlas="ICON_ATLAS_GREATWORKS_2"			Index="37"/>
		<Row Name="ICON_GREATWORK_CASSATT_2"			Atlas="ICON_ATLAS_GREATWORKS_2"			Index="38"/>
		<Row Name="ICON_GREATWORK_CASSATT_3"			Atlas="ICON_ATLAS_GREATWORKS_2"			Index="39"/>
		<Row Name="ICON_GREATWORK_VIVALDI_1"			Atlas="ICON_ATLAS_GREATWORKS"			Index="1"/>
		<Row Name="ICON_GREATWORK_VIVALDI_2"			Atlas="ICON_ATLAS_GREATWORKS"			Index="1"/>
		<Row Name="ICON_GREATWORK_BACH_1"					Atlas="ICON_ATLAS_GREATWORKS"			Index="1"/>
		<Row Name="ICON_GREATWORK_BACH_2"					Atlas="ICON_ATLAS_GREATWORKS"			Index="1"/>
		<Row Name="ICON_GREATWORK_BEETHOVEN_1"		Atlas="ICON_ATLAS_GREATWORKS"			Index="1"/>
		<Row Name="ICON_GREATWORK_BEETHOVEN_2"		Atlas="ICON_ATLAS_GREATWORKS"			Index="1"/>
		<Row Name="ICON_GREATWORK_MOZART_1"				Atlas="ICON_ATLAS_GREATWORKS"			Index="1"/>
		<Row Name="ICON_GREATWORK_MOZART_2"				Atlas="ICON_ATLAS_GREATWORKS"			Index="1"/>
		<Row Name="ICON_GREATWORK_KENGYO_1"				Atlas="ICON_ATLAS_GREATWORKS"			Index="1"/>
		<Row Name="ICON_GREATWORK_KENGYO_2"				Atlas="ICON_ATLAS_GREATWORKS"			Index="1"/>
		<Row Name="ICON_GREATWORK_GOMEZ_1"				Atlas="ICON_ATLAS_GREATWORKS"			Index="1"/>
		<Row Name="ICON_GREATWORK_GOMEZ_2"				Atlas="ICON_ATLAS_GREATWORKS"			Index="1"/>
		<Row Name="ICON_GREATWORK_LISZT_1"				Atlas="ICON_ATLAS_GREATWORKS"			Index="1"/>
		<Row Name="ICON_GREATWORK_LISZT_2"				Atlas="ICON_ATLAS_GREATWORKS"			Index="1"/>
		<Row Name="ICON_GREATWORK_CHOPIN_1"				Atlas="ICON_ATLAS_GREATWORKS"			Index="1"/>
		<Row Name="ICON_GREATWORK_CHOPIN_2"				Atlas="ICON_ATLAS_GREATWORKS"			Index="1"/>
		<Row Name="ICON_GREATWORK_TCHAIKOVSKY_1"	Atlas="ICON_ATLAS_GREATWORKS"			Index="1"/>
		<Row Name="ICON_GREATWORK_TCHAIKOVSKY_2"	Atlas="ICON_ATLAS_GREATWORKS"			Index="1"/>
		<Row Name="ICON_GREATWORK_TIANHUA_1"			Atlas="ICON_ATLAS_GREATWORKS"			Index="1"/>
		<Row Name="ICON_GREATWORK_TIANHUA_2"			Atlas="ICON_ATLAS_GREATWORKS"			Index="1"/>
		<Row Name="ICON_GREATWORK_DVORAK_1"				Atlas="ICON_ATLAS_GREATWORKS"			Index="1"/>
		<Row Name="ICON_GREATWORK_DVORAK_2"				Atlas="ICON_ATLAS_GREATWORKS"			Index="1"/>
		<Row Name="ICON_GREATWORK_SCHUMANN_1"			Atlas="ICON_ATLAS_GREATWORKS"			Index="1"/>
		<Row Name="ICON_GREATWORK_SCHUMANN_2"			Atlas="ICON_ATLAS_GREATWORKS"			Index="1"/>
		<Row Name="ICON_GREATWORK_ROSAS_1"				Atlas="ICON_ATLAS_GREATWORKS"			Index="1"/>
		<Row Name="ICON_GREATWORK_ROSAS_2"				Atlas="ICON_ATLAS_GREATWORKS"			Index="1"/>
		<Row Name="ICON_GREATWORK_LILIUOKALANI_1"	Atlas="ICON_ATLAS_GREATWORKS"			Index="1"/>
		<Row Name="ICON_GREATWORK_LILIUOKALANI_2"	Atlas="ICON_ATLAS_GREATWORKS"			Index="1"/>
		<Row Name="ICON_GREATWORK_JAAN_1"					Atlas="ICON_ATLAS_GREATWORKS"			Index="1"/>
		<Row Name="ICON_GREATWORK_JAAN_2"					Atlas="ICON_ATLAS_GREATWORKS"			Index="1"/>
		<Row Name="ICON_GREATWORK_LEONTOVYCH_1"		Atlas="ICON_ATLAS_GREATWORKS"			Index="1"/>
		<Row Name="ICON_GREATWORK_LEONTOVYCH_2"		Atlas="ICON_ATLAS_GREATWORKS"			Index="1"/>
		<Row Name="ICON_GREATWORK_RELIC_1"				Atlas="ICON_ATLAS_GREATWORKS_2"			Index="17"/>
		<Row Name="ICON_GREATWORK_RELIC_2"				Atlas="ICON_ATLAS_GREATWORKS"			Index="3"/>
		<Row Name="ICON_GREATWORK_RELIC_3"				Atlas="ICON_ATLAS_GREATWORKS"			Index="4"/>
		<Row Name="ICON_GREATWORK_RELIC_4"				Atlas="ICON_ATLAS_GREATWORKS"			Index="5"/>
		<Row Name="ICON_GREATWORK_RELIC_5"				Atlas="ICON_ATLAS_GREATWORKS"			Index="6"/>
		<Row Name="ICON_GREATWORK_RELIC_6"				Atlas="ICON_ATLAS_GREATWORKS"			Index="7"/>
		<Row Name="ICON_GREATWORK_RELIC_7"				Atlas="ICON_ATLAS_GREATWORKS_2"			Index="7"/>
		<Row Name="ICON_GREATWORK_RELIC_8"				Atlas="ICON_ATLAS_GREATWORKS_2"			Index="8"/>
		<Row Name="ICON_GREATWORK_RELIC_9"				Atlas="ICON_ATLAS_GREATWORKS_2"			Index="9"/>
		<Row Name="ICON_GREATWORK_RELIC_10"				Atlas="ICON_ATLAS_GREATWORKS_2"			Index="10"/>
		<Row Name="ICON_GREATWORK_RELIC_11"				Atlas="ICON_ATLAS_GREATWORKS_2"			Index="11"/>
		<Row Name="ICON_GREATWORK_RELIC_12"				Atlas="ICON_ATLAS_GREATWORKS_2"			Index="12"/>
		<Row Name="ICON_GREATWORK_RELIC_13"				Atlas="ICON_ATLAS_GREATWORKS_2"			Index="13"/>
		<Row Name="ICON_GREATWORK_RELIC_14"				Atlas="ICON_ATLAS_GREATWORKS_2"			Index="14"/>
		<Row Name="ICON_GREATWORK_RELIC_15"				Atlas="ICON_ATLAS_GREATWORKS_2"			Index="15"/>
		<Row Name="ICON_GREATWORK_RELIC_16"				Atlas="ICON_ATLAS_GREATWORKS_2"			Index="16"/>
		<Row Name="ICON_GREATWORK_ARTIFACT_1"			Atlas="ICON_ATLAS_GREATWORKS"			Index="8"/>
		<Row Name="ICON_GREATWORK_ARTIFACT_2"			Atlas="ICON_ATLAS_GREATWORKS"			Index="9"/>
		<Row Name="ICON_GREATWORK_ARTIFACT_3"			Atlas="ICON_ATLAS_GREATWORKS"			Index="10"/>
		<Row Name="ICON_GREATWORK_ARTIFACT_4"			Atlas="ICON_ATLAS_GREATWORKS"			Index="11"/>
		<Row Name="ICON_GREATWORK_ARTIFACT_5"			Atlas="ICON_ATLAS_GREATWORKS"			Index="12"/>
		<Row Name="ICON_GREATWORK_ARTIFACT_6"			Atlas="ICON_ATLAS_GREATWORKS"			Index="13"/>
		<Row Name="ICON_GREATWORK_ARTIFACT_7"			Atlas="ICON_ATLAS_GREATWORKS_2"			Index="18"/>
		<Row Name="ICON_GREATWORK_ARTIFACT_8"			Atlas="ICON_ATLAS_GREATWORKS_2"			Index="19"/>
		<Row Name="ICON_GREATWORK_ARTIFACT_9"			Atlas="ICON_ATLAS_GREATWORKS_2"			Index="20"/>
		<Row Name="ICON_GREATWORK_ARTIFACT_10"		Atlas="ICON_ATLAS_GREATWORKS_2"			Index="21"/>
		<Row Name="ICON_GREATWORK_ARTIFACT_11"		Atlas="ICON_ATLAS_GREATWORKS_2"			Index="22"/>
		<Row Name="ICON_GREATWORK_ARTIFACT_12"		Atlas="ICON_ATLAS_GREATWORKS_2"			Index="23"/>
		<Row Name="ICON_GREATWORK_ARTIFACT_13"		Atlas="ICON_ATLAS_GREATWORKS_2"			Index="24"/>
		<Row Name="ICON_GREATWORK_ARTIFACT_14"		Atlas="ICON_ATLAS_GREATWORKS_2"			Index="25"/>
		<Row Name="ICON_GREATWORK_ARTIFACT_15"		Atlas="ICON_ATLAS_GREATWORKS_2"			Index="26"/>
		<Row Name="ICON_GREATWORK_ARTIFACT_16"		Atlas="ICON_ATLAS_GREATWORKS_2"			Index="27"/>
		<Row Name="ICON_GREATWORK_ARTIFACT_17"		Atlas="ICON_ATLAS_GREATWORKS_2"			Index="28"/>
		<Row Name="ICON_GREATWORK_ARTIFACT_18"		Atlas="ICON_ATLAS_GREATWORKS_2"			Index="29"/>
		<Row Name="ICON_GREATWORK_ARTIFACT_19"		Atlas="ICON_ATLAS_GREATWORKS_2"			Index="30"/>
		<Row Name="ICON_GREATWORK_ARTIFACT_20"		Atlas="ICON_ATLAS_GREATWORKS_2"			Index="31"/>
		<Row Name="ICON_GREATWORK_ARTIFACT_21"		Atlas="ICON_ATLAS_GREATWORKS_2"			Index="32"/>
		<Row Name="ICON_GREATWORK_ARTIFACT_22"		Atlas="ICON_ATLAS_GREATWORKS_2"			Index="33"/>
		<Row Name="ICON_GREATWORK_ARTIFACT_23"		Atlas="ICON_ATLAS_GREATWORKS_2"			Index="34"/>
		<Row Name="ICON_GREATWORK_ARTIFACT_24"		Atlas="ICON_ATLAS_GREATWORKS_2"			Index="35"/>
		<Row Name="ICON_GREATWORK_ARTIFACT_25"		Atlas="ICON_ATLAS_GREATWORKS_2"			Index="36"/>
	</IconDefinitions>
</GameInfo>